semanticuiform/__init__.py
semanticuiform/config.py
semanticuiform/meta.py
semanticuiform/models.py
semanticuiform/tests.py
semanticuiform/templates/semanticui/field.html
semanticuiform/templates/semanticui/form.html
semanticuiform/templates/semanticui/formset.html
semanticuiform/templatetags/__init__.py
semanticuiform/templatetags/semanticui.py
django2_semanticui_form-0.0.4.dist-info/LICENSE
django2_semanticui_form-0.0.4.dist-info/METADATA
django2_semanticui_form-0.0.4.dist-info/WHEEL
django2_semanticui_form-0.0.4.dist-info/top_level.txt
django2_semanticui_form-0.0.4.dist-info/RECORD
