Metadata-Version: 2.1
Name: django2-semanticui-form
Version: 0.0.4
Summary: Semantic or Fomantic UI for Django Forms
Home-page: https://github.com/Gokujo/django-semanticui-form
Author: Maxim Harder
Author-email: maxim_harder@jas.de
License: BSD
Keywords: SemanticUI,django,Semantic,Fomantic
Platform: UNKNOWN
Classifier: Programming Language :: Python
Classifier: Topic :: Software Development :: Libraries :: Python Modules
Classifier: Framework :: Django
Classifier: Environment :: Web Environment
Classifier: Programming Language :: Python :: 2
Classifier: Programming Language :: Python :: 2.7
Classifier: Programming Language :: Python :: 3
Classifier: Programming Language :: Python :: 3.3
Classifier: Programming Language :: Python :: 3.4
Classifier: Programming Language :: Python :: 3.5
Classifier: Programming Language :: Python :: 3.6
Requires-Dist: django (>=2.0)
